dasp_pytorch/__init__.py
dasp_pytorch/functional.py
dasp_pytorch/modules.py
dasp_pytorch/signal.py
dasp_pytorch-0.0.1.dist-info/LICENSE
dasp_pytorch-0.0.1.dist-info/METADATA
dasp_pytorch-0.0.1.dist-info/WHEEL
dasp_pytorch-0.0.1.dist-info/top_level.txt
dasp_pytorch-0.0.1.dist-info/RECORD
