Metadata-Version: 2.1
Name: dasp-pytorch
Version: 0.0.1
Summary: Differentiable audio processors in PyTorch.
Home-page: https://github.com/csteinmetz1/dasp-pytorch
Author: Christian Steinmetz
Author-email: c.j.steinmetz@qmul.ac.uk
License: Apache License 2.0
Classifier: License :: OSI Approved :: Apache Software License
Classifier: Topic :: Multimedia :: Sound/Audio
Classifier: Topic :: Scientific/Engineering
Requires-Python: >=3.8.0
License-File: LICENSE
Requires-Dist: torch
Requires-Dist: numpy
Requires-Dist: scipy
Provides-Extra: extra
Requires-Dist: matplotlib ; extra == 'extra'
Requires-Dist: librosa ; extra == 'extra'
